longling/__init__.py
longling/base.py
longling/main.py
longling/dm/__init__.py
longling/dm/utils.py
longling/dm/pdh/__init__.py
longling/dm/pdh/auto_df.py
longling/dm/pdh/auto_df_eda.py
longling/dm/pdh/loading.py
longling/dm/pdh/op.py
longling/dm/preprocessing/__init__.py
longling/dm/preprocessing/preprocessing.py
longling/infrastructure/__init__.py
longling/infrastructure/config.py
longling/infrastructure/install_file.py
longling/infrastructure/utils.py
longling/infrastructure/cli/__init__.py
longling/infrastructure/cli/main.py
longling/infrastructure/cli/units.py
longling/infrastructure/install_proj/__init__.py
longling/infrastructure/install_proj/docs_proj.py
longling/infrastructure/install_proj/py_proj.py
longling/infrastructure/install_proj/web_proj.py
longling/infrastructure/meta_docs/.pypirc.template
longling/infrastructure/meta_docs/.travis.yml
longling/infrastructure/meta_docs/Makefile.template
longling/infrastructure/meta_docs/pyproject.toml
longling/infrastructure/meta_docs/pytest.ini
longling/infrastructure/meta_docs/setup.cfg.template
longling/infrastructure/meta_docs/setup.py.template
longling/infrastructure/meta_docs/Dockerfile/nginx.docker
longling/infrastructure/meta_docs/Dockerfile/python-cli.docker
longling/infrastructure/meta_docs/Dockerfile/python-flask.docker
longling/infrastructure/meta_docs/chart/.helmignore
longling/infrastructure/meta_docs/chart/Chart.yaml
longling/infrastructure/meta_docs/chart/values.yaml
longling/infrastructure/meta_docs/chart/templates/NOTES.txt
longling/infrastructure/meta_docs/chart/templates/_helpers.tpl
longling/infrastructure/meta_docs/chart/templates/deployment.yaml
longling/infrastructure/meta_docs/chart/templates/ingress.yaml
longling/infrastructure/meta_docs/chart/templates/secret.yaml
longling/infrastructure/meta_docs/chart/templates/service.yaml
longling/infrastructure/meta_docs/chart/templates/serviceaccount.yaml
longling/infrastructure/meta_docs/chart/templates/tests/test-connection.yaml
longling-1.4.3.dist-info/LICENSE
longling-1.4.3.dist-info/METADATA
longling-1.4.3.dist-info/WHEEL
longling-1.4.3.dist-info/entry_points.txt
longling-1.4.3.dist-info/top_level.txt
longling-1.4.3.dist-info/RECORD
