Metadata-Version: 2.1
Name: longling
Version: 1.4.3
Summary: This project aims to provide some handy toolkit functions to help construct the architecture.
Home-page: https://gitlab.com/tswsxk/longling.git
Author: Sherlock, Shiwei Tong
Author-email: tongsw@mail.ustc.edu.cn
License: LICENSE.txt
Classifier: Programming Language :: Python :: 3
Classifier: Programming Language :: Python :: 3.8
Classifier: Programming Language :: Python :: 3.9
Classifier: Programming Language :: Python :: 3.10
Classifier: Programming Language :: Python :: 3.11
Classifier: Programming Language :: Python :: 3.12
Classifier: Environment :: Other Environment
Classifier: Intended Audience :: Developers
Classifier: License :: OSI Approved :: Mozilla Public License 2.0 (MPL 2.0)
Classifier: Operating System :: OS Independent
Classifier: Topic :: Software Development :: Libraries :: Python Modules
Requires-Python: >=3.8
License-File: LICENSE
Requires-Dist: pip
Requires-Dist: tqdm
Requires-Dist: fire
Requires-Dist: PyYAML >=5.1
Requires-Dist: toml
Requires-Dist: multiprocess
Requires-Dist: joblib
Provides-Extra: dev
Requires-Dist: pytest >=4 ; extra == 'dev'
Requires-Dist: pytest-cov >=2.6.0 ; extra == 'dev'
Requires-Dist: flake8 ; extra == 'dev'
Requires-Dist: sphinx ; extra == 'dev'
Requires-Dist: sphinx-rtd-theme ; extra == 'dev'
Requires-Dist: nbsphinx ; extra == 'dev'
Requires-Dist: m2r2 ; extra == 'dev'
Requires-Dist: Image ; extra == 'dev'
Requires-Dist: recommonmark ; extra == 'dev'
Requires-Dist: ipython ; extra == 'dev'
Requires-Dist: sphinx-toggleprompt ; extra == 'dev'
Requires-Dist: setuptools >=40 ; extra == 'dev'
Requires-Dist: wheel ; extra == 'dev'
Requires-Dist: twine ; extra == 'dev'
Provides-Extra: dm
Requires-Dist: pandas >=2.0 ; extra == 'dm'
Requires-Dist: numpy ; extra == 'dm'
Requires-Dist: matplotlib ; extra == 'dm'
Provides-Extra: doc
Requires-Dist: sphinx ; extra == 'doc'
Requires-Dist: sphinx-rtd-theme ; extra == 'doc'
Requires-Dist: nbsphinx ; extra == 'doc'
Requires-Dist: m2r2 ; extra == 'doc'
Requires-Dist: Image ; extra == 'doc'
Requires-Dist: recommonmark ; extra == 'doc'
Requires-Dist: ipython ; extra == 'doc'
Requires-Dist: sphinx-toggleprompt ; extra == 'doc'
Provides-Extra: full
Requires-Dist: pandas ; extra == 'full'
Requires-Dist: numpy >=1.16.5 ; extra == 'full'
Requires-Dist: scipy ; extra == 'full'
Requires-Dist: scikit-learn ; extra == 'full'
Requires-Dist: nni ; extra == 'full'
Requires-Dist: matplotlib ; extra == 'full'
Requires-Dist: tensorboardx ; extra == 'full'
Requires-Dist: tensorboard ; extra == 'full'
Requires-Dist: requests ; extra == 'full'
Requires-Dist: rarfile ; extra == 'full'
Requires-Dist: bs4 ; extra == 'full'
Requires-Dist: lxml ; extra == 'full'
Requires-Dist: urllib3 ; extra == 'full'
Provides-Extra: ml
Requires-Dist: pandas ; extra == 'ml'
Requires-Dist: numpy >=1.16.5 ; extra == 'ml'
Requires-Dist: scipy ; extra == 'ml'
Requires-Dist: scikit-learn ; extra == 'ml'
Requires-Dist: nni ; extra == 'ml'
Provides-Extra: ml-full
Requires-Dist: pandas ; extra == 'ml-full'
Requires-Dist: numpy >=1.16.5 ; extra == 'ml-full'
Requires-Dist: scipy ; extra == 'ml-full'
Requires-Dist: scikit-learn ; extra == 'ml-full'
Requires-Dist: nni ; extra == 'ml-full'
Requires-Dist: matplotlib ; extra == 'ml-full'
Requires-Dist: tensorboardx ; extra == 'ml-full'
Requires-Dist: tensorboard ; extra == 'ml-full'
Provides-Extra: ml-viz
Requires-Dist: pandas ; extra == 'ml-viz'
Requires-Dist: numpy >=1.16.5 ; extra == 'ml-viz'
Requires-Dist: scipy ; extra == 'ml-viz'
Requires-Dist: scikit-learn ; extra == 'ml-viz'
Requires-Dist: nni ; extra == 'ml-viz'
Requires-Dist: matplotlib ; extra == 'ml-viz'
Requires-Dist: tensorboardx ; extra == 'ml-viz'
Requires-Dist: tensorboard ; extra == 'ml-viz'
Provides-Extra: spider
Requires-Dist: requests ; extra == 'spider'
Requires-Dist: rarfile ; extra == 'spider'
Requires-Dist: bs4 ; extra == 'spider'
Requires-Dist: lxml ; extra == 'spider'
Requires-Dist: urllib3 ; extra == 'spider'
Provides-Extra: test
Requires-Dist: pytest >=4 ; extra == 'test'
Requires-Dist: pytest-cov >=2.6.0 ; extra == 'test'
Requires-Dist: flake8 ; extra == 'test'
Requires-Dist: pandas ; extra == 'test'
Requires-Dist: numpy >=1.16.5 ; extra == 'test'
Requires-Dist: scipy ; extra == 'test'
Requires-Dist: scikit-learn ; extra == 'test'
Requires-Dist: nni ; extra == 'test'
Requires-Dist: matplotlib ; extra == 'test'
Requires-Dist: tensorboardx ; extra == 'test'
Requires-Dist: tensorboard ; extra == 'test'
Requires-Dist: requests ; extra == 'test'
Requires-Dist: rarfile ; extra == 'test'
Requires-Dist: bs4 ; extra == 'test'
Requires-Dist: lxml ; extra == 'test'
Requires-Dist: urllib3 ; extra == 'test'
Provides-Extra: viz
Requires-Dist: matplotlib ; extra == 'viz'
Requires-Dist: tensorboardx ; extra == 'viz'
Requires-Dist: tensorboard ; extra == 'viz'
